descriptor/__init__.py
descriptor/base.py
descriptor/error.py
descriptor/interface.py
descriptor/util.py
descriptor/validator.py
descriptor/support/__init__.py
descriptor/support/base.py
descriptor/support/error.py
descriptor/support/interface.py
descriptor/support/json.py
test/__init__.py
test/base.py
test/data.py
field_descriptor-1.0.1.dist-info/LICENSE
field_descriptor-1.0.1.dist-info/METADATA
field_descriptor-1.0.1.dist-info/WHEEL
field_descriptor-1.0.1.dist-info/top_level.txt
field_descriptor-1.0.1.dist-info/RECORD
