Metadata-Version: 2.1
Name: field-descriptor
Version: 1.0.1
Summary: A descriptor package
Home-page: https://github.com/BlueWhaleMain/descriptor
Author: BlueWhaleMain
Author-email: bluewhalemain@outlook.com
License: MIT License
Platform: all
Classifier: Intended Audience :: Developers
Classifier: Operating System :: OS Independent
Classifier: Natural Language :: Chinese (Simplified)
Classifier: Programming Language :: Python
Classifier: Programming Language :: Python :: 3.6
Classifier: Programming Language :: Python :: 3.7
Classifier: Programming Language :: Python :: 3.9
Classifier: Topic :: Software Development :: Libraries
Requires-Python: >=3.6.0
License-File: LICENSE
